apolloarchive/.env.example
apolloarchive/__init__.py
apolloarchive/cli.py
apolloarchive/download.py
apolloarchive/env.py
apolloarchive/flickr.py
apolloarchive/vars.py
apollo_archive-1.3.dist-info/AUTHORS
apollo_archive-1.3.dist-info/LICENSE.md
apollo_archive-1.3.dist-info/METADATA
apollo_archive-1.3.dist-info/WHEEL
apollo_archive-1.3.dist-info/entry_points.txt
apollo_archive-1.3.dist-info/pbr.json
apollo_archive-1.3.dist-info/top_level.txt
apollo_archive-1.3.dist-info/RECORD
