Metadata-Version: 2.1
Name: apollo-archive
Version: 1.3
Summary: Python package to list and download all original images from Flickr Apollo Archive
Home-page: https://github.com/seignovert/python-flickr-apollo-archive
Author: Benoit Seignovert
Author-email: benoit.a.seignovert@jpl.nasa.gov
License: MIT
Keywords: flickr,nasa,apollo,api,image
Platform: UNKNOWN
Classifier: Development Status :: 4 - Beta
Classifier: Intended Audience :: Science/Research
Classifier: Intended Audience :: Developers
Classifier: Natural Language :: English
Classifier: License :: OSI Approved :: MIT License
Classifier: Programming Language :: Python
Classifier: Programming Language :: Python :: 3.6
Classifier: Topic :: Scientific/Engineering
Classifier: Topic :: Scientific/Engineering :: Astronomy
Requires-Dist: flickrapi
Requires-Dist: python-slugify
Requires-Dist: wget
Requires-Dist: tqdm
Requires-Dist: argparse
